hparm/__init__.py
hparm/hparm.py
hparm-0.0.2.dist-info/LICENSE
hparm-0.0.2.dist-info/METADATA
hparm-0.0.2.dist-info/WHEEL
hparm-0.0.2.dist-info/top_level.txt
hparm-0.0.2.dist-info/RECORD
