Metadata-Version: 2.1
Name: hparm
Version: 0.0.2
Summary: Loads yaml file to a python structure
Author: knoriy
Author-email: <knoriy@bournemouth.ac.uk>
License: UNKNOWN
Keywords: python,yaml
Platform: UNKNOWN
Classifier: Development Status :: 5 - Production/Stable
Classifier: Intended Audience :: Developers
Classifier: Programming Language :: Python :: 3
Classifier: Operating System :: Unix
Classifier: Operating System :: MacOS :: MacOS X
Classifier: Operating System :: Microsoft :: Windows
License-File: LICENSE
Requires-Dist: PyYAML
